<invoice><part>
  <date>08/21/2024</date>
  <group>Previous Activity</group>
  <group-id>1</group-id>
  <description>Payment by Credit Card Visa (1460) </description>
  <amount>-25.00</amount>
</part>
<part>
  <group>contracts</group>
  <days>Mon-Fri</days>
  <group-id>2</group-id>
  <group-two>Declan Kearney's Consistent Schedule Contract</group-two>
  <start-date>08/01/2024</start-date>
  <end-date>08/31/2024</end-date>
  <site>Everett Beacon Middle School - 8th Grade | Octavo Grado</site>
  <rate>Everett Rate (1 x $0.00/Month)</rate>
  <amount>0.00</amount>
</part>
<part>
  <date>08/21/2024</date>
  <group>Discounts and Adjustments</group>
  <group-id>3</group-id>
  <description>Everett Registration Fee for 24-25 School Year | Mission Graduates Program</description>
  <amount>25.00</amount>
</part>
</invoice>